kankube.py
kankube-0.5.2.dist-info/DESCRIPTION.rst
kankube-0.5.2.dist-info/METADATA
kankube-0.5.2.dist-info/RECORD
kankube-0.5.2.dist-info/WHEEL
kankube-0.5.2.dist-info/entry_points.txt
kankube-0.5.2.dist-info/metadata.json
kankube-0.5.2.dist-info/top_level.txt
