Metadata-Version: 2.0
Name: kankube
Version: 0.5.2
Summary: Basic kubectl wrapper
Home-page: https://github.com/kandoio/kankube
Author: Kando Limited
Author-email: admin@kando.io
License: BSD license
Keywords: kankube
Platform: UNKNOWN
Classifier: Development Status :: 2 - Pre-Alpha
Classifier: Intended Audience :: Developers
Classifier: License :: OSI Approved :: BSD License
Classifier: Natural Language :: English
Classifier: Programming Language :: Python :: 2
Classifier: Programming Language :: Python :: 2.6
Classifier: Programming Language :: Python :: 2.7
Classifier: Programming Language :: Python :: 3
Classifier: Programming Language :: Python :: 3.3
Classifier: Programming Language :: Python :: 3.4
Classifier: Programming Language :: Python :: 3.5
Requires-Dist: pyyaml
